pyModSlave/ModFactory.py
pyModSlave/ModSlaveAbout.py
pyModSlave/ModSlaveBusMonitor.py
pyModSlave/ModSlaveMBData.py
pyModSlave/ModSlaveMBDataItemDelegate.py
pyModSlave/ModSlaveMBDataModel.py
pyModSlave/ModSlaveSettings.py
pyModSlave/ModSlaveSettingsRTU.py
pyModSlave/ModSlaveSettingsTCP.py
pyModSlave/RepeatTimer.py
pyModSlave/Ui_about.py
pyModSlave/Ui_busmonitor.py
pyModSlave/Ui_mainwindow.py
pyModSlave/Ui_settings.py
pyModSlave/Ui_settingsModbusRTU.py
pyModSlave/Ui_settingsModbusTCP.py
pyModSlave/Utils.py
pyModSlave/__init__.py
pyModSlave/pyModSlave.py
pyModSlave/pyModSlaveQt_rc.py
pyModSlave/ManModbus/exceptions.html
pyModSlave/ManModbus/func_descr.html
pyModSlave/ManModbus/funcs.html
pyModSlave/ManModbus/index.html
pyModSlave/ManModbus/links.html
pyModSlave/ManModbus/READ_ME/HTML5WebTemplates.co.uk.url
pyModSlave/ManModbus/READ_ME/PLEASE READ.txt
pyModSlave/ManModbus/READ_ME/Remove the footer link.URL
pyModSlave/ManModbus/style/Thumbs.db
pyModSlave/ManModbus/style/background.png
pyModSlave/ManModbus/style/bullet.png
pyModSlave/ManModbus/style/graphic.png
pyModSlave/ManModbus/style/header.jpg
pyModSlave/ManModbus/style/link.png
pyModSlave/ManModbus/style/search.png
pyModSlave/ManModbus/style/style.css
pyModSlave/ManModbus/style/transparent.png
pyModSlave/ManModbus/style/transparent_light.png
pyModSlave/modbus_tk/__init__.py
pyModSlave/modbus_tk/defines.py
pyModSlave/modbus_tk/exceptions.py
pyModSlave/modbus_tk/hooks.py
pyModSlave/modbus_tk/modbus.py
pyModSlave/modbus_tk/modbus_rtu.py
pyModSlave/modbus_tk/modbus_tcp.py
pyModSlave/modbus_tk/simulator.py
pyModSlave/modbus_tk/simulator_rpc_client.py
pyModSlave/modbus_tk/utils.py
pyModSlave/ui/about.ui
pyModSlave/ui/busmonitor.ui
pyModSlave/ui/mainwindow.ui
pyModSlave/ui/settings.ui
pyModSlave/ui/settingsmodbusrtu.ui
pyModSlave/ui/settingsmodbustcp.ui
pyModSlave/ui/icons/AI.png
pyModSlave/ui/icons/AO.png
pyModSlave/ui/icons/Bus.ico
pyModSlave/ui/icons/Bus.png
pyModSlave/ui/icons/Close-16.png
pyModSlave/ui/icons/DI.png
pyModSlave-0.4.3.2.dist-info/LICENSE
pyModSlave-0.4.3.2.dist-info/METADATA
pyModSlave-0.4.3.2.dist-info/WHEEL
pyModSlave-0.4.3.2.dist-info/top_level.txt
pyModSlave-0.4.3.2.dist-info/RECORD
