Metadata-Version: 2.1
Name: pyModSlave
Version: 0.4.3.2
Summary: A modbus RTU/TCP slave application
Home-page: https://sourceforge.net/projects/pymodslave/
Author: ElBar
Author-email: eleftherios.barbas@gmail.com
License: UNKNOWN
Platform: UNKNOWN
Classifier: Programming Language :: Python :: 3
Classifier: License :: OSI Approved :: GNU General Public License v3 (GPLv3)
Classifier: Operating System :: OS Independent
